{
	"start":	{
		"connected":	[{
				"socket":	5,
				"local_host":	"192.168.1.1",
				"local_port":	46308,
				"remote_host":	"192.168.8.2",
				"remote_port":	5206
			}],
		"version":	"iperf 3.5",
		"system_info":	"Linux h1 4.18.0-372.13.1.el8_6.x86_64 #1 SMP Wed Jun 29 17:21:09 UTC 2022 x86_64",
		"timestamp":	{
			"time":	"Wed, 20 Dec 2023 21:56:03 GMT",
			"timesecs":	1703109363
		},
		"connecting_to":	{
			"host":	"192.168.8.2",
			"port":	5206
		},
		"cookie":	"pncdazcyzpuwoikk7raesuxsn7bdid5c6o5f",
		"tcp_mss_default":	1448,
		"sock_bufsize":	0,
		"sndbuf_actual":	16384,
		"rcvbuf_actual":	87380,
		"test_start":	{
			"protocol":	"TCP",
			"num_streams":	1,
			"blksize":	131072,
			"omit":	0,
			"duration":	0,
			"bytes":	1073741824,
			"blocks":	0,
			"reverse":	0,
			"tos":	8
		}
	},
	"intervals":	[{
			"streams":	[{
					"socket":	5,
					"start":	0,
					"end":	2.0002009868621826,
					"seconds":	2.0002009868621826,
					"bytes":	3439000,
					"bits_per_second":	13754617.751268826,
					"retransmits":	0,
					"snd_cwnd":	529968,
					"rtt":	256397,
					"rttvar":	1915,
					"pmtu":	1500,
					"omitted":	false
				}],
			"sum":	{
				"start":	0,
				"end":	2.0002009868621826,
				"seconds":	2.0002009868621826,
				"bytes":	3439000,
				"bits_per_second":	13754617.751268826,
				"retransmits":	0,
				"omitted":	false
			}
		}, {
			"streams":	[{
					"socket":	5,
					"start":	2.0002009868621826,
					"end":	4.0003252029418945,
					"seconds":	2.0001242160797119,
					"bytes":	4959680,
					"bits_per_second":	19837487.932508845,
					"retransmits":	0,
					"snd_cwnd":	760200,
					"rtt":	279595,
					"rttvar":	134,
					"pmtu":	1500,
					"omitted":	false
				}],
			"sum":	{
				"start":	2.0002009868621826,
				"end":	4.0003252029418945,
				"seconds":	2.0001242160797119,
				"bytes":	4959680,
				"bits_per_second":	19837487.932508845,
				"retransmits":	0,
				"omitted":	false
			}
		}, {
			"streams":	[{
					"socket":	5,
					"start":	4.0003252029418945,
					"end":	6.0005640983581543,
					"seconds":	2.0002388954162598,
					"bytes":	5242880,
					"bits_per_second":	20969015.299180772,
					"retransmits":	0,
					"snd_cwnd":	1048352,
					"rtt":	305255,
					"rttvar":	5198,
					"pmtu":	1500,
					"omitted":	false
				}],
			"sum":	{
				"start":	4.0003252029418945,
				"end":	6.0005640983581543,
				"seconds":	2.0002388954162598,
				"bytes":	5242880,
				"bits_per_second":	20969015.299180772,
				"retransmits":	0,
				"omitted":	false
			}
		}, {
			"streams":	[{
					"socket":	5,
					"start":	6.0005640983581543,
					"end":	8.00008511543274,
					"seconds":	1.999521017074585,
					"bytes":	9175040,
					"bits_per_second":	36708951.480484523,
					"retransmits":	0,
					"snd_cwnd":	1446552,
					"rtt":	334244,
					"rttvar":	209,
					"pmtu":	1500,
					"omitted":	false
				}],
			"sum":	{
				"start":	6.0005640983581543,
				"end":	8.00008511543274,
				"seconds":	1.999521017074585,
				"bytes":	9175040,
				"bits_per_second":	36708951.480484523,
				"retransmits":	0,
				"omitted":	false
			}
		}, {
			"streams":	[{
					"socket":	5,
					"start":	8.00008511543274,
					"end":	10.000290155410767,
					"seconds":	2.0002050399780273,
					"bytes":	7864320,
					"bits_per_second":	31454055.330593072,
					"retransmits":	0,
					"snd_cwnd":	1882400,
					"rtt":	368918,
					"rttvar":	184,
					"pmtu":	1500,
					"omitted":	false
				}],
			"sum":	{
				"start":	8.00008511543274,
				"end":	10.000290155410767,
				"seconds":	2.0002050399780273,
				"bytes":	7864320,
				"bits_per_second":	31454055.330593072,
				"retransmits":	0,
				"omitted":	false
			}
		}, {
			"streams":	[{
					"socket":	5,
					"start":	10.000290155410767,
					"end":	12.000310182571411,
					"seconds":	2.0000200271606445,
					"bytes":	10485760,
					"bits_per_second":	41942620.004205659,
					"retransmits":	0,
					"snd_cwnd":	2402232,
					"rtt":	408678,
					"rttvar":	1376,
					"pmtu":	1500,
					"omitted":	false
				}],
			"sum":	{
				"start":	10.000290155410767,
				"end":	12.000310182571411,
				"seconds":	2.0000200271606445,
				"bytes":	10485760,
				"bits_per_second":	41942620.004205659,
				"retransmits":	0,
				"omitted":	false
			}
		}, {
			"streams":	[{
					"socket":	5,
					"start":	12.000310182571411,
					"end":	14.000126123428345,
					"seconds":	1.9998159408569336,
					"bytes":	13107200,
					"bits_per_second":	52433625.444083549,
					"retransmits":	0,
					"snd_cwnd":	3016184,
					"rtt":	460151,
					"rttvar":	292,
					"pmtu":	1500,
					"omitted":	false
				}],
			"sum":	{
				"start":	12.000310182571411,
				"end":	14.000126123428345,
				"seconds":	1.9998159408569336,
				"bytes":	13107200,
				"bits_per_second":	52433625.444083549,
				"retransmits":	0,
				"omitted":	false
			}
		}, {
			"streams":	[{
					"socket":	5,
					"start":	14.000126123428345,
					"end":	16.000087022781372,
					"seconds":	1.9999608993530273,
					"bytes":	11752200,
					"bits_per_second":	47009719.055214532,
					"retransmits":	0,
					"snd_cwnd":	3146504,
					"rtt":	445811,
					"rttvar":	6736,
					"pmtu":	1500,
					"omitted":	false
				}],
			"sum":	{
				"start":	14.000126123428345,
				"end":	16.000087022781372,
				"seconds":	1.9999608993530273,
				"bytes":	11752200,
				"bits_per_second":	47009719.055214532,
				"retransmits":	0,
				"omitted":	false
			}
		}, {
			"streams":	[{
					"socket":	5,
					"start":	16.000087022781372,
					"end":	18.000195026397705,
					"seconds":	2.000108003616333,
					"bytes":	11788680,
					"bits_per_second":	47152173.697361365,
					"retransmits":	0,
					"snd_cwnd":	3146504,
					"rtt":	481785,
					"rttvar":	920,
					"pmtu":	1500,
					"omitted":	false
				}],
			"sum":	{
				"start":	16.000087022781372,
				"end":	18.000195026397705,
				"seconds":	2.000108003616333,
				"bytes":	11788680,
				"bits_per_second":	47152173.697361365,
				"retransmits":	0,
				"omitted":	false
			}
		}, {
			"streams":	[{
					"socket":	5,
					"start":	18.000195026397705,
					"end":	20.000121116638184,
					"seconds":	1.9999260902404785,
					"bytes":	11752480,
					"bits_per_second":	47011657.310143247,
					"retransmits":	0,
					"snd_cwnd":	3146504,
					"rtt":	482910,
					"rttvar":	835,
					"pmtu":	1500,
					"omitted":	false
				}],
			"sum":	{
				"start":	18.000195026397705,
				"end":	20.000121116638184,
				"seconds":	1.9999260902404785,
				"bytes":	11752480,
				"bits_per_second":	47011657.310143247,
				"retransmits":	0,
				"omitted":	false
			}
		}, {
			"streams":	[{
					"socket":	5,
					"start":	20.000121116638184,
					"end":	22.000271081924438,
					"seconds":	2.0001499652862549,
					"bytes":	11796480,
					"bits_per_second":	47182382.140278071,
					"retransmits":	0,
					"snd_cwnd":	3146504,
					"rtt":	482886,
					"rttvar":	834,
					"pmtu":	1500,
					"omitted":	false
				}],
			"sum":	{
				"start":	20.000121116638184,
				"end":	22.000271081924438,
				"seconds":	2.0001499652862549,
				"bytes":	11796480,
				"bits_per_second":	47182382.140278071,
				"retransmits":	0,
				"omitted":	false
			}
		}, {
			"streams":	[{
					"socket":	5,
					"start":	22.000271081924438,
					"end":	24.000087022781372,
					"seconds":	1.9998159408569336,
					"bytes":	13107200,
					"bits_per_second":	52433625.444083549,
					"retransmits":	0,
					"snd_cwnd":	4785640,
					"rtt":	470496,
					"rttvar":	9193,
					"pmtu":	1500,
					"omitted":	false
				}],
			"sum":	{
				"start":	22.000271081924438,
				"end":	24.000087022781372,
				"seconds":	1.9998159408569336,
				"bytes":	13107200,
				"bits_per_second":	52433625.444083549,
				"retransmits":	0,
				"omitted":	false
			}
		}, {
			"streams":	[{
					"socket":	5,
					"start":	24.000087022781372,
					"end":	26.000328063964844,
					"seconds":	2.0002410411834717,
					"bytes":	10485760,
					"bits_per_second":	41937985.609158173,
					"retransmits":	0,
					"snd_cwnd":	4785640,
					"rtt":	476672,
					"rttvar":	1558,
					"pmtu":	1500,
					"omitted":	false
				}],
			"sum":	{
				"start":	24.000087022781372,
				"end":	26.000328063964844,
				"seconds":	2.0002410411834717,
				"bytes":	10485760,
				"bits_per_second":	41937985.609158173,
				"retransmits":	0,
				"omitted":	false
			}
		}, {
			"streams":	[{
					"socket":	5,
					"start":	26.000328063964844,
					"end":	28.000144004821777,
					"seconds":	1.9998159408569336,
					"bytes":	13107200,
					"bits_per_second":	52433625.444083549,
					"retransmits":	0,
					"snd_cwnd":	4785640,
					"rtt":	482572,
					"rttvar":	395,
					"pmtu":	1500,
					"omitted":	false
				}],
			"sum":	{
				"start":	26.000328063964844,
				"end":	28.000144004821777,
				"seconds":	1.9998159408569336,
				"bytes":	13107200,
				"bits_per_second":	52433625.444083549,
				"retransmits":	0,
				"omitted":	false
			}
		}, {
			"streams":	[{
					"socket":	5,
					"start":	28.000144004821777,
					"end":	30.000086069107056,
					"seconds":	1.9999420642852783,
					"bytes":	11796480,
					"bits_per_second":	47187286.914596587,
					"retransmits":	0,
					"snd_cwnd":	4785640,
					"rtt":	445983,
					"rttvar":	3890,
					"pmtu":	1500,
					"omitted":	false
				}],
			"sum":	{
				"start":	28.000144004821777,
				"end":	30.000086069107056,
				"seconds":	1.9999420642852783,
				"bytes":	11796480,
				"bits_per_second":	47187286.914596587,
				"retransmits":	0,
				"omitted":	false
			}
		}, {
			"streams":	[{
					"socket":	5,
					"start":	30.000086069107056,
					"end":	32.000186204910278,
					"seconds":	2.0001001358032227,
					"bytes":	11796480,
					"bits_per_second":	47183557.618279494,
					"retransmits":	0,
					"snd_cwnd":	4785640,
					"rtt":	482323,
					"rttvar":	360,
					"pmtu":	1500,
					"omitted":	false
				}],
			"sum":	{
				"start":	30.000086069107056,
				"end":	32.000186204910278,
				"seconds":	2.0001001358032227,
				"bytes":	11796480,
				"bits_per_second":	47183557.618279494,
				"retransmits":	0,
				"omitted":	false
			}
		}, {
			"streams":	[{
					"socket":	5,
					"start":	32.000186204910278,
					"end":	34.000110149383545,
					"seconds":	1.9999239444732666,
					"bytes":	11796480,
					"bits_per_second":	47187714.443238661,
					"retransmits":	0,
					"snd_cwnd":	4785640,
					"rtt":	480476,
					"rttvar":	2020,
					"pmtu":	1500,
					"omitted":	false
				}],
			"sum":	{
				"start":	32.000186204910278,
				"end":	34.000110149383545,
				"seconds":	1.9999239444732666,
				"bytes":	11796480,
				"bits_per_second":	47187714.443238661,
				"retransmits":	0,
				"omitted":	false
			}
		}, {
			"streams":	[{
					"socket":	5,
					"start":	34.000110149383545,
					"end":	36.000250101089478,
					"seconds":	2.0001399517059326,
					"bytes":	11796480,
					"bits_per_second":	47182618.356035352,
					"retransmits":	0,
					"snd_cwnd":	4785640,
					"rtt":	477165,
					"rttvar":	1755,
					"pmtu":	1500,
					"omitted":	false
				}],
			"sum":	{
				"start":	34.000110149383545,
				"end":	36.000250101089478,
				"seconds":	2.0001399517059326,
				"bytes":	11796480,
				"bits_per_second":	47182618.356035352,
				"retransmits":	0,
				"omitted":	false
			}
		}, {
			"streams":	[{
					"socket":	5,
					"start":	36.000250101089478,
					"end":	38.000087022781372,
					"seconds":	1.9998369216918945,
					"bytes":	13107200,
					"bits_per_second":	52433075.348608308,
					"retransmits":	0,
					"snd_cwnd":	4785640,
					"rtt":	454673,
					"rttvar":	5815,
					"pmtu":	1500,
					"omitted":	false
				}],
			"sum":	{
				"start":	36.000250101089478,
				"end":	38.000087022781372,
				"seconds":	1.9998369216918945,
				"bytes":	13107200,
				"bits_per_second":	52433075.348608308,
				"retransmits":	0,
				"omitted":	false
			}
		}, {
			"streams":	[{
					"socket":	5,
					"start":	38.000087022781372,
					"end":	40.000310182571411,
					"seconds":	2.0002231597900391,
					"bytes":	10485760,
					"bits_per_second":	41938360.522135645,
					"retransmits":	0,
					"snd_cwnd":	4785640,
					"rtt":	482550,
					"rttvar":	617,
					"pmtu":	1500,
					"omitted":	false
				}],
			"sum":	{
				"start":	38.000087022781372,
				"end":	40.000310182571411,
				"seconds":	2.0002231597900391,
				"bytes":	10485760,
				"bits_per_second":	41938360.522135645,
				"retransmits":	0,
				"omitted":	false
			}
		}, {
			"streams":	[{
					"socket":	5,
					"start":	40.000310182571411,
					"end":	42.000110149383545,
					"seconds":	1.9997999668121338,
					"bytes":	13107200,
					"bits_per_second":	52434044.274514474,
					"retransmits":	0,
					"snd_cwnd":	4785640,
					"rtt":	482197,
					"rttvar":	348,
					"pmtu":	1500,
					"omitted":	false
				}],
			"sum":	{
				"start":	40.000310182571411,
				"end":	42.000110149383545,
				"seconds":	1.9997999668121338,
				"bytes":	13107200,
				"bits_per_second":	52434044.274514474,
				"retransmits":	0,
				"omitted":	false
			}
		}, {
			"streams":	[{
					"socket":	5,
					"start":	42.000110149383545,
					"end":	44.000360012054443,
					"seconds":	2.0002498626708984,
					"bytes":	10485760,
					"bits_per_second":	41937800.65455842,
					"retransmits":	0,
					"snd_cwnd":	4785640,
					"rtt":	459480,
					"rttvar":	15639,
					"pmtu":	1500,
					"omitted":	false
				}],
			"sum":	{
				"start":	42.000110149383545,
				"end":	44.000360012054443,
				"seconds":	2.0002498626708984,
				"bytes":	10485760,
				"bits_per_second":	41937800.65455842,
				"retransmits":	0,
				"omitted":	false
			}
		}, {
			"streams":	[{
					"socket":	5,
					"start":	44.000360012054443,
					"end":	46.000166177749634,
					"seconds":	1.9998061656951904,
					"bytes":	13107200,
					"bits_per_second":	52433881.742508017,
					"retransmits":	0,
					"snd_cwnd":	4785640,
					"rtt":	482103,
					"rttvar":	343,
					"pmtu":	1500,
					"omitted":	false
				}],
			"sum":	{
				"start":	44.000360012054443,
				"end":	46.000166177749634,
				"seconds":	1.9998061656951904,
				"bytes":	13107200,
				"bits_per_second":	52433881.742508017,
				"retransmits":	0,
				"omitted":	false
			}
		}, {
			"streams":	[{
					"socket":	5,
					"start":	46.000166177749634,
					"end":	48.000087022781372,
					"seconds":	1.9999208450317383,
					"bytes":	11796480,
					"bits_per_second":	47187787.57391388,
					"retransmits":	0,
					"snd_cwnd":	4785640,
					"rtt":	471695,
					"rttvar":	5155,
					"pmtu":	1500,
					"omitted":	false
				}],
			"sum":	{
				"start":	46.000166177749634,
				"end":	48.000087022781372,
				"seconds":	1.9999208450317383,
				"bytes":	11796480,
				"bits_per_second":	47187787.57391388,
				"retransmits":	0,
				"omitted":	false
			}
		}, {
			"streams":	[{
					"socket":	5,
					"start":	48.000087022781372,
					"end":	50.000216007232666,
					"seconds":	2.0001289844512939,
					"bytes":	11796480,
					"bits_per_second":	47182877.071245246,
					"retransmits":	0,
					"snd_cwnd":	4785640,
					"rtt":	482969,
					"rttvar":	634,
					"pmtu":	1500,
					"omitted":	false
				}],
			"sum":	{
				"start":	48.000087022781372,
				"end":	50.000216007232666,
				"seconds":	2.0001289844512939,
				"bytes":	11796480,
				"bits_per_second":	47182877.071245246,
				"retransmits":	0,
				"omitted":	false
			}
		}, {
			"streams":	[{
					"socket":	5,
					"start":	50.000216007232666,
					"end":	52.000130176544189,
					"seconds":	1.9999141693115234,
					"bytes":	11796480,
					"bits_per_second":	47187945.086907305,
					"retransmits":	0,
					"snd_cwnd":	4785640,
					"rtt":	482489,
					"rttvar":	505,
					"pmtu":	1500,
					"omitted":	false
				}],
			"sum":	{
				"start":	50.000216007232666,
				"end":	52.000130176544189,
				"seconds":	1.9999141693115234,
				"bytes":	11796480,
				"bits_per_second":	47187945.086907305,
				"retransmits":	0,
				"omitted":	false
			}
		}, {
			"streams":	[{
					"socket":	5,
					"start":	52.000130176544189,
					"end":	54.00026798248291,
					"seconds":	2.0001378059387207,
					"bytes":	11796480,
					"bits_per_second":	47182668.974005342,
					"retransmits":	0,
					"snd_cwnd":	4785640,
					"rtt":	481585,
					"rttvar":	725,
					"pmtu":	1500,
					"omitted":	false
				}],
			"sum":	{
				"start":	52.000130176544189,
				"end":	54.00026798248291,
				"seconds":	2.0001378059387207,
				"bytes":	11796480,
				"bits_per_second":	47182668.974005342,
				"retransmits":	0,
				"omitted":	false
			}
		}, {
			"streams":	[{
					"socket":	5,
					"start":	54.00026798248291,
					"end":	56.000087022781372,
					"seconds":	1.9998190402984619,
					"bytes":	13107200,
					"bits_per_second":	52433544.179252632,
					"retransmits":	0,
					"snd_cwnd":	4785640,
					"rtt":	467206,
					"rttvar":	9390,
					"pmtu":	1500,
					"omitted":	false
				}],
			"sum":	{
				"start":	54.00026798248291,
				"end":	56.000087022781372,
				"seconds":	1.9998190402984619,
				"bytes":	13107200,
				"bits_per_second":	52433544.179252632,
				"retransmits":	0,
				"omitted":	false
			}
		}, {
			"streams":	[{
					"socket":	5,
					"start":	56.000087022781372,
					"end":	58.000325202941895,
					"seconds":	2.0002381801605225,
					"bytes":	10485760,
					"bits_per_second":	41938045.594784118,
					"retransmits":	0,
					"snd_cwnd":	4785640,
					"rtt":	482449,
					"rttvar":	430,
					"pmtu":	1500,
					"omitted":	false
				}],
			"sum":	{
				"start":	56.000087022781372,
				"end":	58.000325202941895,
				"seconds":	2.0002381801605225,
				"bytes":	10485760,
				"bits_per_second":	41938045.594784118,
				"retransmits":	0,
				"omitted":	false
			}
		}, {
			"streams":	[{
					"socket":	5,
					"start":	58.000325202941895,
					"end":	60.000130176544189,
					"seconds":	1.9998049736022949,
					"bytes":	13107200,
					"bits_per_second":	52433912.998584844,
					"retransmits":	0,
					"snd_cwnd":	4785640,
					"rtt":	481779,
					"rttvar":	597,
					"pmtu":	1500,
					"omitted":	false
				}],
			"sum":	{
				"start":	58.000325202941895,
				"end":	60.000130176544189,
				"seconds":	1.9998049736022949,
				"bytes":	13107200,
				"bits_per_second":	52433912.998584844,
				"retransmits":	0,
				"omitted":	false
			}
		}, {
			"streams":	[{
					"socket":	5,
					"start":	60.000130176544189,
					"end":	62.000101089477539,
					"seconds":	1.9999709129333496,
					"bytes":	11796480,
					"bits_per_second":	47186606.259980641,
					"retransmits":	0,
					"snd_cwnd":	4785640,
					"rtt":	451833,
					"rttvar":	5510,
					"pmtu":	1500,
					"omitted":	false
				}],
			"sum":	{
				"start":	60.000130176544189,
				"end":	62.000101089477539,
				"seconds":	1.9999709129333496,
				"bytes":	11796480,
				"bits_per_second":	47186606.259980641,
				"retransmits":	0,
				"omitted":	false
			}
		}, {
			"streams":	[{
					"socket":	5,
					"start":	62.000101089477539,
					"end":	64.000204086303711,
					"seconds":	2.0001029968261719,
					"bytes":	11796480,
					"bits_per_second":	47183490.1251347,
					"retransmits":	0,
					"snd_cwnd":	4785640,
					"rtt":	480276,
					"rttvar":	278,
					"pmtu":	1500,
					"omitted":	false
				}],
			"sum":	{
				"start":	62.000101089477539,
				"end":	64.000204086303711,
				"seconds":	2.0001029968261719,
				"bytes":	11796480,
				"bits_per_second":	47183490.1251347,
				"retransmits":	0,
				"omitted":	false
			}
		}, {
			"streams":	[{
					"socket":	5,
					"start":	64.000204086303711,
					"end":	66.000157117843628,
					"seconds":	1.999953031539917,
					"bytes":	11796480,
					"bits_per_second":	47187028.151024073,
					"retransmits":	0,
					"snd_cwnd":	4785640,
					"rtt":	482857,
					"rttvar":	985,
					"pmtu":	1500,
					"omitted":	false
				}],
			"sum":	{
				"start":	64.000204086303711,
				"end":	66.000157117843628,
				"seconds":	1.999953031539917,
				"bytes":	11796480,
				"bits_per_second":	47187028.151024073,
				"retransmits":	0,
				"omitted":	false
			}
		}, {
			"streams":	[{
					"socket":	5,
					"start":	66.000157117843628,
					"end":	68.000262975692749,
					"seconds":	2.0001058578491211,
					"bytes":	11796480,
					"bits_per_second":	47183422.632182993,
					"retransmits":	0,
					"snd_cwnd":	4785640,
					"rtt":	478336,
					"rttvar":	438,
					"pmtu":	1500,
					"omitted":	false
				}],
			"sum":	{
				"start":	66.000157117843628,
				"end":	68.000262975692749,
				"seconds":	2.0001058578491211,
				"bytes":	11796480,
				"bits_per_second":	47183422.632182993,
				"retransmits":	0,
				"omitted":	false
			}
		}, {
			"streams":	[{
					"socket":	5,
					"start":	68.000262975692749,
					"end":	70.000087022781372,
					"seconds":	1.999824047088623,
					"bytes":	13107200,
					"bits_per_second":	52433412.905827105,
					"retransmits":	0,
					"snd_cwnd":	4785640,
					"rtt":	462587,
					"rttvar":	12594,
					"pmtu":	1500,
					"omitted":	false
				}],
			"sum":	{
				"start":	68.000262975692749,
				"end":	70.000087022781372,
				"seconds":	1.999824047088623,
				"bytes":	13107200,
				"bits_per_second":	52433412.905827105,
				"retransmits":	0,
				"omitted":	false
			}
		}, {
			"streams":	[{
					"socket":	5,
					"start":	70.000087022781372,
					"end":	72.000333070755,
					"seconds":	2.0002460479736328,
					"bytes":	10485760,
					"bits_per_second":	41937880.634725682,
					"retransmits":	0,
					"snd_cwnd":	4785640,
					"rtt":	477966,
					"rttvar":	1545,
					"pmtu":	1500,
					"omitted":	false
				}],
			"sum":	{
				"start":	70.000087022781372,
				"end":	72.000333070755,
				"seconds":	2.0002460479736328,
				"bytes":	10485760,
				"bits_per_second":	41937880.634725682,
				"retransmits":	0,
				"omitted":	false
			}
		}, {
			"streams":	[{
					"socket":	5,
					"start":	72.000333070755,
					"end":	74.000145196914673,
					"seconds":	1.999812126159668,
					"bytes":	13107200,
					"bits_per_second":	52433725.4626828,
					"retransmits":	0,
					"snd_cwnd":	4785640,
					"rtt":	479225,
					"rttvar":	338,
					"pmtu":	1500,
					"omitted":	false
				}],
			"sum":	{
				"start":	72.000333070755,
				"end":	74.000145196914673,
				"seconds":	1.999812126159668,
				"bytes":	13107200,
				"bits_per_second":	52433725.4626828,
				"retransmits":	0,
				"omitted":	false
			}
		}, {
			"streams":	[{
					"socket":	5,
					"start":	74.000145196914673,
					"end":	76.000089168548584,
					"seconds":	1.9999439716339111,
					"bytes":	11796480,
					"bits_per_second":	47187241.912032284,
					"retransmits":	0,
					"snd_cwnd":	4785640,
					"rtt":	458937,
					"rttvar":	6665,
					"pmtu":	1500,
					"omitted":	false
				}],
			"sum":	{
				"start":	74.000145196914673,
				"end":	76.000089168548584,
				"seconds":	1.9999439716339111,
				"bytes":	11796480,
				"bits_per_second":	47187241.912032284,
				"retransmits":	0,
				"omitted":	false
			}
		}, {
			"streams":	[{
					"socket":	5,
					"start":	76.000089168548584,
					"end":	78.00018310546875,
					"seconds":	2.000093936920166,
					"bytes":	11796480,
					"bits_per_second":	47183703.854088962,
					"retransmits":	0,
					"snd_cwnd":	4785640,
					"rtt":	482413,
					"rttvar":	556,
					"pmtu":	1500,
					"omitted":	false
				}],
			"sum":	{
				"start":	76.000089168548584,
				"end":	78.00018310546875,
				"seconds":	2.000093936920166,
				"bytes":	11796480,
				"bits_per_second":	47183703.854088962,
				"retransmits":	0,
				"omitted":	false
			}
		}, {
			"streams":	[{
					"socket":	5,
					"start":	78.00018310546875,
					"end":	80.000116109848022,
					"seconds":	1.9999330043792725,
					"bytes":	11796480,
					"bits_per_second":	47187500.67794925,
					"retransmits":	0,
					"snd_cwnd":	4785640,
					"rtt":	482562,
					"rttvar":	637,
					"pmtu":	1500,
					"omitted":	false
				}],
			"sum":	{
				"start":	78.00018310546875,
				"end":	80.000116109848022,
				"seconds":	1.9999330043792725,
				"bytes":	11796480,
				"bits_per_second":	47187500.67794925,
				"retransmits":	0,
				"omitted":	false
			}
		}, {
			"streams":	[{
					"socket":	5,
					"start":	80.000116109848022,
					"end":	82.0002601146698,
					"seconds":	2.0001440048217773,
					"bytes":	11796480,
					"bits_per_second":	47182522.744610578,
					"retransmits":	0,
					"snd_cwnd":	4785640,
					"rtt":	482111,
					"rttvar":	187,
					"pmtu":	1500,
					"omitted":	false
				}],
			"sum":	{
				"start":	80.000116109848022,
				"end":	82.0002601146698,
				"seconds":	2.0001440048217773,
				"bytes":	11796480,
				"bits_per_second":	47182522.744610578,
				"retransmits":	0,
				"omitted":	false
			}
		}, {
			"streams":	[{
					"socket":	5,
					"start":	82.0002601146698,
					"end":	84.000086069107056,
					"seconds":	1.9998259544372559,
					"bytes":	13107200,
					"bits_per_second":	52433362.897075996,
					"retransmits":	0,
					"snd_cwnd":	4785640,
					"rtt":	456254,
					"rttvar":	4012,
					"pmtu":	1500,
					"omitted":	false
				}],
			"sum":	{
				"start":	82.0002601146698,
				"end":	84.000086069107056,
				"seconds":	1.9998259544372559,
				"bytes":	13107200,
				"bits_per_second":	52433362.897075996,
				"retransmits":	0,
				"omitted":	false
			}
		}, {
			"streams":	[{
					"socket":	5,
					"start":	84.000086069107056,
					"end":	86.000316143035889,
					"seconds":	2.000230073928833,
					"bytes":	10485760,
					"bits_per_second":	41938215.554989509,
					"retransmits":	0,
					"snd_cwnd":	4785640,
					"rtt":	482233,
					"rttvar":	147,
					"pmtu":	1500,
					"omitted":	false
				}],
			"sum":	{
				"start":	84.000086069107056,
				"end":	86.000316143035889,
				"seconds":	2.000230073928833,
				"bytes":	10485760,
				"bits_per_second":	41938215.554989509,
				"retransmits":	0,
				"omitted":	false
			}
		}, {
			"streams":	[{
					"socket":	5,
					"start":	86.000316143035889,
					"end":	88.000111103057861,
					"seconds":	1.9997949600219727,
					"bytes":	13107200,
					"bits_per_second":	52434175.551101439,
					"retransmits":	0,
					"snd_cwnd":	4785640,
					"rtt":	482230,
					"rttvar":	266,
					"pmtu":	1500,
					"omitted":	false
				}],
			"sum":	{
				"start":	86.000316143035889,
				"end":	88.000111103057861,
				"seconds":	1.9997949600219727,
				"bytes":	13107200,
				"bits_per_second":	52434175.551101439,
				"retransmits":	0,
				"omitted":	false
			}
		}, {
			"streams":	[{
					"socket":	5,
					"start":	88.000111103057861,
					"end":	90.000358104705811,
					"seconds":	2.0002470016479492,
					"bytes":	10485760,
					"bits_per_second":	41937860.63965527,
					"retransmits":	0,
					"snd_cwnd":	4785640,
					"rtt":	452084,
					"rttvar":	7161,
					"pmtu":	1500,
					"omitted":	false
				}],
			"sum":	{
				"start":	88.000111103057861,
				"end":	90.000358104705811,
				"seconds":	2.0002470016479492,
				"bytes":	10485760,
				"bits_per_second":	41937860.63965527,
				"retransmits":	0,
				"omitted":	false
			}
		}, {
			"streams":	[{
					"socket":	5,
					"start":	90.000358104705811,
					"end":	92.0001699924469,
					"seconds":	1.9998118877410889,
					"bytes":	13107200,
					"bits_per_second":	52433731.713857919,
					"retransmits":	0,
					"snd_cwnd":	4785640,
					"rtt":	483613,
					"rttvar":	343,
					"pmtu":	1500,
					"omitted":	false
				}],
			"sum":	{
				"start":	90.000358104705811,
				"end":	92.0001699924469,
				"seconds":	1.9998118877410889,
				"bytes":	13107200,
				"bits_per_second":	52433731.713857919,
				"retransmits":	0,
				"omitted":	false
			}
		}, {
			"streams":	[{
					"socket":	5,
					"start":	92.0001699924469,
					"end":	94.000087022781372,
					"seconds":	1.9999170303344727,
					"bytes":	11796288,
					"bits_per_second":	47187109.549348257,
					"retransmits":	0,
					"snd_cwnd":	4785640,
					"rtt":	475212,
					"rttvar":	11251,
					"pmtu":	1500,
					"omitted":	false
				}],
			"sum":	{
				"start":	92.0001699924469,
				"end":	94.000087022781372,
				"seconds":	1.9999170303344727,
				"bytes":	11796288,
				"bits_per_second":	47187109.549348257,
				"retransmits":	0,
				"omitted":	false
			}
		}, {
			"streams":	[{
					"socket":	5,
					"start":	94.000087022781372,
					"end":	96.00021505355835,
					"seconds":	2.0001280307769775,
					"bytes":	11796480,
					"bits_per_second":	47182899.568354107,
					"retransmits":	0,
					"snd_cwnd":	4785640,
					"rtt":	482282,
					"rttvar":	345,
					"pmtu":	1500,
					"omitted":	false
				}],
			"sum":	{
				"start":	94.000087022781372,
				"end":	96.00021505355835,
				"seconds":	2.0001280307769775,
				"bytes":	11796480,
				"bits_per_second":	47182899.568354107,
				"retransmits":	0,
				"omitted":	false
			}
		}, {
			"streams":	[{
					"socket":	5,
					"start":	96.00021505355835,
					"end":	98.000128030776978,
					"seconds":	1.9999129772186279,
					"bytes":	11791200,
					"bits_per_second":	47166852.295337655,
					"retransmits":	0,
					"snd_cwnd":	4785640,
					"rtt":	487358,
					"rttvar":	454,
					"pmtu":	1500,
					"omitted":	false
				}],
			"sum":	{
				"start":	96.00021505355835,
				"end":	98.000128030776978,
				"seconds":	1.9999129772186279,
				"bytes":	11791200,
				"bits_per_second":	47166852.295337655,
				"retransmits":	0,
				"omitted":	false
			}
		}, {
			"streams":	[{
					"socket":	5,
					"start":	98.000128030776978,
					"end":	100.00026702880859,
					"seconds":	2.0001389980316162,
					"bytes":	11796480,
					"bits_per_second":	47182640.852897495,
					"retransmits":	0,
					"snd_cwnd":	4785640,
					"rtt":	482766,
					"rttvar":	239,
					"pmtu":	1500,
					"omitted":	false
				}],
			"sum":	{
				"start":	98.000128030776978,
				"end":	100.00026702880859,
				"seconds":	2.0001389980316162,
				"bytes":	11796480,
				"bits_per_second":	47182640.852897495,
				"retransmits":	0,
				"omitted":	false
			}
		}, {
			"streams":	[{
					"socket":	5,
					"start":	100.00026702880859,
					"end":	102.00009512901306,
					"seconds":	1.9998281002044678,
					"bytes":	13107200,
					"bits_per_second":	52433306.637345016,
					"retransmits":	0,
					"snd_cwnd":	4785640,
					"rtt":	462371,
					"rttvar":	10312,
					"pmtu":	1500,
					"omitted":	false
				}],
			"sum":	{
				"start":	100.00026702880859,
				"end":	102.00009512901306,
				"seconds":	1.9998281002044678,
				"bytes":	13107200,
				"bits_per_second":	52433306.637345016,
				"retransmits":	0,
				"omitted":	false
			}
		}, {
			"streams":	[{
					"socket":	5,
					"start":	102.00009512901306,
					"end":	104.00032114982605,
					"seconds":	2.0002260208129883,
					"bytes":	10485760,
					"bits_per_second":	41938300.5356088,
					"retransmits":	0,
					"snd_cwnd":	4785640,
					"rtt":	487105,
					"rttvar":	10387,
					"pmtu":	1500,
					"omitted":	false
				}],
			"sum":	{
				"start":	102.00009512901306,
				"end":	104.00032114982605,
				"seconds":	2.0002260208129883,
				"bytes":	10485760,
				"bits_per_second":	41938300.5356088,
				"retransmits":	0,
				"omitted":	false
			}
		}, {
			"streams":	[{
					"socket":	5,
					"start":	104.00032114982605,
					"end":	106.00012397766113,
					"seconds":	1.999802827835083,
					"bytes":	13107200,
					"bits_per_second":	52433969.259617053,
					"retransmits":	0,
					"snd_cwnd":	4785640,
					"rtt":	484360,
					"rttvar":	1215,
					"pmtu":	1500,
					"omitted":	false
				}],
			"sum":	{
				"start":	104.00032114982605,
				"end":	106.00012397766113,
				"seconds":	1.999802827835083,
				"bytes":	13107200,
				"bits_per_second":	52433969.259617053,
				"retransmits":	0,
				"omitted":	false
			}
		}, {
			"streams":	[{
					"socket":	5,
					"start":	106.00012397766113,
					"end":	108.00008606910706,
					"seconds":	1.9999620914459229,
					"bytes":	11796480,
					"bits_per_second":	47186814.391952552,
					"retransmits":	0,
					"snd_cwnd":	4785640,
					"rtt":	443164,
					"rttvar":	3806,
					"pmtu":	1500,
					"omitted":	false
				}],
			"sum":	{
				"start":	106.00012397766113,
				"end":	108.00008606910706,
				"seconds":	1.9999620914459229,
				"bytes":	11796480,
				"bits_per_second":	47186814.391952552,
				"retransmits":	0,
				"omitted":	false
			}
		}, {
			"streams":	[{
					"socket":	5,
					"start":	108.00008606910706,
					"end":	110.00017714500427,
					"seconds":	2.0000910758972168,
					"bytes":	11796480,
					"bits_per_second":	47183771.347845212,
					"retransmits":	0,
					"snd_cwnd":	4785640,
					"rtt":	482455,
					"rttvar":	489,
					"pmtu":	1500,
					"omitted":	false
				}],
			"sum":	{
				"start":	108.00008606910706,
				"end":	110.00017714500427,
				"seconds":	2.0000910758972168,
				"bytes":	11796480,
				"bits_per_second":	47183771.347845212,
				"retransmits":	0,
				"omitted":	false
			}
		}, {
			"streams":	[{
					"socket":	5,
					"start":	110.00017714500427,
					"end":	112.00010204315186,
					"seconds":	1.999924898147583,
					"bytes":	11796480,
					"bits_per_second":	47187691.941538043,
					"retransmits":	0,
					"snd_cwnd":	4785640,
					"rtt":	480501,
					"rttvar":	3924,
					"pmtu":	1500,
					"omitted":	false
				}],
			"sum":	{
				"start":	110.00017714500427,
				"end":	112.00010204315186,
				"seconds":	1.999924898147583,
				"bytes":	11796480,
				"bits_per_second":	47187691.941538043,
				"retransmits":	0,
				"omitted":	false
			}
		}, {
			"streams":	[{
					"socket":	5,
					"start":	112.00010204315186,
					"end":	114.00023198127747,
					"seconds":	2.0001299381256104,
					"bytes":	11796480,
					"bits_per_second":	47182854.574157842,
					"retransmits":	0,
					"snd_cwnd":	4785640,
					"rtt":	477138,
					"rttvar":	1847,
					"pmtu":	1500,
					"omitted":	false
				}],
			"sum":	{
				"start":	112.00010204315186,
				"end":	114.00023198127747,
				"seconds":	2.0001299381256104,
				"bytes":	11796480,
				"bits_per_second":	47182854.574157842,
				"retransmits":	0,
				"omitted":	false
			}
		}, {
			"streams":	[{
					"socket":	5,
					"start":	114.00023198127747,
					"end":	116.00008511543274,
					"seconds":	1.9998531341552734,
					"bytes":	13107200,
					"bits_per_second":	52432650.282737516,
					"retransmits":	0,
					"snd_cwnd":	4785640,
					"rtt":	452681,
					"rttvar":	6815,
					"pmtu":	1500,
					"omitted":	false
				}],
			"sum":	{
				"start":	114.00023198127747,
				"end":	116.00008511543274,
				"seconds":	1.9998531341552734,
				"bytes":	13107200,
				"bits_per_second":	52432650.282737516,
				"retransmits":	0,
				"omitted":	false
			}
		}, {
			"streams":	[{
					"socket":	5,
					"start":	116.00008511543274,
					"end":	118.00028610229492,
					"seconds":	2.0002009868621826,
					"bytes":	10485760,
					"bits_per_second":	41938825.423537247,
					"retransmits":	0,
					"snd_cwnd":	4785640,
					"rtt":	482341,
					"rttvar":	340,
					"pmtu":	1500,
					"omitted":	false
				}],
			"sum":	{
				"start":	116.00008511543274,
				"end":	118.00028610229492,
				"seconds":	2.0002009868621826,
				"bytes":	10485760,
				"bits_per_second":	41938825.423537247,
				"retransmits":	0,
				"omitted":	false
			}
		}, {
			"streams":	[{
					"socket":	5,
					"start":	118.00028610229492,
					"end":	120.00009107589722,
					"seconds":	1.9998049736022949,
					"bytes":	13107200,
					"bits_per_second":	52433912.998584844,
					"retransmits":	0,
					"snd_cwnd":	4785640,
					"rtt":	482036,
					"rttvar":	1624,
					"pmtu":	1500,
					"omitted":	false
				}],
			"sum":	{
				"start":	118.00028610229492,
				"end":	120.00009107589722,
				"seconds":	1.9998049736022949,
				"bytes":	13107200,
				"bits_per_second":	52433912.998584844,
				"retransmits":	0,
				"omitted":	false
			}
		}, {
			"streams":	[{
					"socket":	5,
					"start":	120.00009107589722,
					"end":	122.00033807754517,
					"seconds":	2.0002470016479492,
					"bytes":	10485760,
					"bits_per_second":	41937860.63965527,
					"retransmits":	0,
					"snd_cwnd":	4785640,
					"rtt":	481423,
					"rttvar":	1676,
					"pmtu":	1500,
					"omitted":	false
				}],
			"sum":	{
				"start":	120.00009107589722,
				"end":	122.00033807754517,
				"seconds":	2.0002470016479492,
				"bytes":	10485760,
				"bits_per_second":	41937860.63965527,
				"retransmits":	0,
				"omitted":	false
			}
		}, {
			"streams":	[{
					"socket":	5,
					"start":	122.00033807754517,
					"end":	124.00014400482178,
					"seconds":	1.9998059272766113,
					"bytes":	13107200,
					"bits_per_second":	52433887.9937204,
					"retransmits":	0,
					"snd_cwnd":	4785640,
					"rtt":	482403,
					"rttvar":	391,
					"pmtu":	1500,
					"omitted":	false
				}],
			"sum":	{
				"start":	122.00033807754517,
				"end":	124.00014400482178,
				"seconds":	1.9998059272766113,
				"bytes":	13107200,
				"bits_per_second":	52433887.9937204,
				"retransmits":	0,
				"omitted":	false
			}
		}, {
			"streams":	[{
					"socket":	5,
					"start":	124.00014400482178,
					"end":	126.00008916854858,
					"seconds":	1.9999451637268066,
					"bytes":	11796480,
					"bits_per_second":	47187213.78547319,
					"retransmits":	0,
					"snd_cwnd":	4785640,
					"rtt":	450749,
					"rttvar":	4759,
					"pmtu":	1500,
					"omitted":	false
				}],
			"sum":	{
				"start":	124.00014400482178,
				"end":	126.00008916854858,
				"seconds":	1.9999451637268066,
				"bytes":	11796480,
				"bits_per_second":	47187213.78547319,
				"retransmits":	0,
				"omitted":	false
			}
		}, {
			"streams":	[{
					"socket":	5,
					"start":	126.00008916854858,
					"end":	128.00019121170044,
					"seconds":	2.0001020431518555,
					"bytes":	11796480,
					"bits_per_second":	47183512.622828178,
					"retransmits":	0,
					"snd_cwnd":	4785640,
					"rtt":	488151,
					"rttvar":	10655,
					"pmtu":	1500,
					"omitted":	false
				}],
			"sum":	{
				"start":	126.00008916854858,
				"end":	128.00019121170044,
				"seconds":	2.0001020431518555,
				"bytes":	11796480,
				"bits_per_second":	47183512.622828178,
				"retransmits":	0,
				"omitted":	false
			}
		}, {
			"streams":	[{
					"socket":	5,
					"start":	128.00019121170044,
					"end":	130.00010800361633,
					"seconds":	1.9999167919158936,
					"bytes":	11796480,
					"bits_per_second":	47187883.206677333,
					"retransmits":	0,
					"snd_cwnd":	4785640,
					"rtt":	482727,
					"rttvar":	524,
					"pmtu":	1500,
					"omitted":	false
				}],
			"sum":	{
				"start":	128.00019121170044,
				"end":	130.00010800361633,
				"seconds":	1.9999167919158936,
				"bytes":	11796480,
				"bits_per_second":	47187883.206677333,
				"retransmits":	0,
				"omitted":	false
			}
		}, {
			"streams":	[{
					"socket":	5,
					"start":	130.00010800361633,
					"end":	132.00025606155396,
					"seconds":	2.0001480579376221,
					"bytes":	11796480,
					"bits_per_second":	47182427.1335733,
					"retransmits":	0,
					"snd_cwnd":	4785640,
					"rtt":	482323,
					"rttvar":	381,
					"pmtu":	1500,
					"omitted":	false
				}],
			"sum":	{
				"start":	130.00010800361633,
				"end":	132.00025606155396,
				"seconds":	2.0001480579376221,
				"bytes":	11796480,
				"bits_per_second":	47182427.1335733,
				"retransmits":	0,
				"omitted":	false
			}
		}, {
			"streams":	[{
					"socket":	5,
					"start":	132.00025606155396,
					"end":	134.00008702278137,
					"seconds":	1.999830961227417,
					"bytes":	13107200,
					"bits_per_second":	52433231.624558188,
					"retransmits":	0,
					"snd_cwnd":	4785640,
					"rtt":	449881,
					"rttvar":	4975,
					"pmtu":	1500,
					"omitted":	false
				}],
			"sum":	{
				"start":	132.00025606155396,
				"end":	134.00008702278137,
				"seconds":	1.999830961227417,
				"bytes":	13107200,
				"bits_per_second":	52433231.624558188,
				"retransmits":	0,
				"omitted":	false
			}
		}, {
			"streams":	[{
					"socket":	5,
					"start":	134.00008702278137,
					"end":	136.00030207633972,
					"seconds":	2.0002150535583496,
					"bytes":	10485760,
					"bits_per_second":	41938530.484893635,
					"retransmits":	0,
					"snd_cwnd":	4785640,
					"rtt":	487670,
					"rttvar":	10740,
					"pmtu":	1500,
					"omitted":	false
				}],
			"sum":	{
				"start":	134.00008702278137,
				"end":	136.00030207633972,
				"seconds":	2.0002150535583496,
				"bytes":	10485760,
				"bits_per_second":	41938530.484893635,
				"retransmits":	0,
				"omitted":	false
			}
		}, {
			"streams":	[{
					"socket":	5,
					"start":	136.00030207633972,
					"end":	138.00010704994202,
					"seconds":	1.9998049736022949,
					"bytes":	13107200,
					"bits_per_second":	52433912.998584844,
					"retransmits":	0,
					"snd_cwnd":	4785640,
					"rtt":	483705,
					"rttvar":	353,
					"pmtu":	1500,
					"omitted":	false
				}],
			"sum":	{
				"start":	136.00030207633972,
				"end":	138.00010704994202,
				"seconds":	1.9998049736022949,
				"bytes":	13107200,
				"bits_per_second":	52433912.998584844,
				"retransmits":	0,
				"omitted":	false
			}
		}, {
			"streams":	[{
					"socket":	5,
					"start":	138.00010704994202,
					"end":	140.00034999847412,
					"seconds":	2.0002429485321045,
					"bytes":	10485760,
					"bits_per_second":	41937945.618836209,
					"retransmits":	0,
					"snd_cwnd":	4785640,
					"rtt":	481981,
					"rttvar":	260,
					"pmtu":	1500,
					"omitted":	false
				}],
			"sum":	{
				"start":	138.00010704994202,
				"end":	140.00034999847412,
				"seconds":	2.0002429485321045,
				"bytes":	10485760,
				"bits_per_second":	41937945.618836209,
				"retransmits":	0,
				"omitted":	false
			}
		}, {
			"streams":	[{
					"socket":	5,
					"start":	140.00034999847412,
					"end":	142.00015711784363,
					"seconds":	1.9998071193695068,
					"bytes":	13107200,
					"bits_per_second":	52433856.737673372,
					"retransmits":	0,
					"snd_cwnd":	4785640,
					"rtt":	476960,
					"rttvar":	1724,
					"pmtu":	1500,
					"omitted":	false
				}],
			"sum":	{
				"start":	140.00034999847412,
				"end":	142.00015711784363,
				"seconds":	1.9998071193695068,
				"bytes":	13107200,
				"bits_per_second":	52433856.737673372,
				"retransmits":	0,
				"omitted":	false
			}
		}, {
			"streams":	[{
					"socket":	5,
					"start":	142.00015711784363,
					"end":	144.00008511543274,
					"seconds":	1.9999279975891113,
					"bytes":	11796480,
					"bits_per_second":	47187618.811159253,
					"retransmits":	0,
					"snd_cwnd":	4785640,
					"rtt":	458181,
					"rttvar":	11686,
					"pmtu":	1500,
					"omitted":	false
				}],
			"sum":	{
				"start":	142.00015711784363,
				"end":	144.00008511543274,
				"seconds":	1.9999279975891113,
				"bytes":	11796480,
				"bits_per_second":	47187618.811159253,
				"retransmits":	0,
				"omitted":	false
			}
		}, {
			"streams":	[{
					"socket":	5,
					"start":	144.00008511543274,
					"end":	146.00020813941956,
					"seconds":	2.0001230239868164,
					"bytes":	11796480,
					"bits_per_second":	47183017.678527579,
					"retransmits":	0,
					"snd_cwnd":	4785640,
					"rtt":	480992,
					"rttvar":	738,
					"pmtu":	1500,
					"omitted":	false
				}],
			"sum":	{
				"start":	144.00008511543274,
				"end":	146.00020813941956,
				"seconds":	2.0001230239868164,
				"bytes":	11796480,
				"bits_per_second":	47183017.678527579,
				"retransmits":	0,
				"omitted":	false
			}
		}, {
			"streams":	[{
					"socket":	5,
					"start":	146.00020813941956,
					"end":	148.00012016296387,
					"seconds":	1.9999120235443115,
					"bytes":	11796480,
					"bits_per_second":	47187995.716307081,
					"retransmits":	0,
					"snd_cwnd":	4785640,
					"rtt":	482783,
					"rttvar":	943,
					"pmtu":	1500,
					"omitted":	false
				}],
			"sum":	{
				"start":	146.00020813941956,
				"end":	148.00012016296387,
				"seconds":	1.9999120235443115,
				"bytes":	11796480,
				"bits_per_second":	47187995.716307081,
				"retransmits":	0,
				"omitted":	false
			}
		}, {
			"streams":	[{
					"socket":	5,
					"start":	148.00012016296387,
					"end":	150.00026297569275,
					"seconds":	2.0001428127288818,
					"bytes":	11796480,
					"bits_per_second":	47182550.865577638,
					"retransmits":	0,
					"snd_cwnd":	4785640,
					"rtt":	487422,
					"rttvar":	10429,
					"pmtu":	1500,
					"omitted":	false
				}],
			"sum":	{
				"start":	148.00012016296387,
				"end":	150.00026297569275,
				"seconds":	2.0001428127288818,
				"bytes":	11796480,
				"bits_per_second":	47182550.865577638,
				"retransmits":	0,
				"omitted":	false
			}
		}, {
			"streams":	[{
					"socket":	5,
					"start":	150.00026297569275,
					"end":	152.00008606910706,
					"seconds":	1.9998230934143066,
					"bytes":	19660800,
					"bits_per_second":	78650156.865357652,
					"retransmits":	0,
					"snd_cwnd":	4785640,
					"rtt":	246863,
					"rttvar":	7654,
					"pmtu":	1500,
					"omitted":	false
				}],
			"sum":	{
				"start":	150.00026297569275,
				"end":	152.00008606910706,
				"seconds":	1.9998230934143066,
				"bytes":	19660800,
				"bits_per_second":	78650156.865357652,
				"retransmits":	0,
				"omitted":	false
			}
		}, {
			"streams":	[{
					"socket":	5,
					"start":	152.00008606910706,
					"end":	154.00009918212891,
					"seconds":	2.0000131130218506,
					"bytes":	23592960,
					"bits_per_second":	94371221.254056811,
					"retransmits":	0,
					"snd_cwnd":	4785640,
					"rtt":	261231,
					"rttvar":	1814,
					"pmtu":	1500,
					"omitted":	false
				}],
			"sum":	{
				"start":	152.00008606910706,
				"end":	154.00009918212891,
				"seconds":	2.0000131130218506,
				"bytes":	23592960,
				"bits_per_second":	94371221.254056811,
				"retransmits":	0,
				"omitted":	false
			}
		}, {
			"streams":	[{
					"socket":	5,
					"start":	154.00009918212891,
					"end":	156.00012612342834,
					"seconds":	2.0000269412994385,
					"bytes":	23592960,
					"bits_per_second":	94370568.76712434,
					"retransmits":	0,
					"snd_cwnd":	4785640,
					"rtt":	263153,
					"rttvar":	502,
					"pmtu":	1500,
					"omitted":	false
				}],
			"sum":	{
				"start":	154.00009918212891,
				"end":	156.00012612342834,
				"seconds":	2.0000269412994385,
				"bytes":	23592960,
				"bits_per_second":	94370568.76712434,
				"retransmits":	0,
				"omitted":	false
			}
		}, {
			"streams":	[{
					"socket":	5,
					"start":	156.00012612342834,
					"end":	158.00008511543274,
					"seconds":	1.9999589920043945,
					"bytes":	24903680,
					"bits_per_second":	99616762.54188028,
					"retransmits":	0,
					"snd_cwnd":	4785640,
					"rtt":	240981,
					"rttvar":	5087,
					"pmtu":	1500,
					"omitted":	false
				}],
			"sum":	{
				"start":	156.00012612342834,
				"end":	158.00008511543274,
				"seconds":	1.9999589920043945,
				"bytes":	24903680,
				"bits_per_second":	99616762.54188028,
				"retransmits":	0,
				"omitted":	false
			}
		}, {
			"streams":	[{
					"socket":	5,
					"start":	158.00008511543274,
					"end":	160.00008606910706,
					"seconds":	2.0000009536743164,
					"bytes":	23592960,
					"bits_per_second":	94371795.000021458,
					"retransmits":	0,
					"snd_cwnd":	4785640,
					"rtt":	244984,
					"rttvar":	7620,
					"pmtu":	1500,
					"omitted":	false
				}],
			"sum":	{
				"start":	158.00008511543274,
				"end":	160.00008606910706,
				"seconds":	2.0000009536743164,
				"bytes":	23592960,
				"bits_per_second":	94371795.000021458,
				"retransmits":	0,
				"omitted":	false
			}
		}, {
			"streams":	[{
					"socket":	5,
					"start":	160.00008606910706,
					"end":	162.0001380443573,
					"seconds":	2.0000519752502441,
					"bytes":	22282240,
					"bits_per_second":	89126643.810192272,
					"retransmits":	13,
					"snd_cwnd":	3350672,
					"rtt":	262134,
					"rttvar":	681,
					"pmtu":	1500,
					"omitted":	false
				}],
			"sum":	{
				"start":	160.00008606910706,
				"end":	162.0001380443573,
				"seconds":	2.0000519752502441,
				"bytes":	22282240,
				"bits_per_second":	89126643.810192272,
				"retransmits":	13,
				"omitted":	false
			}
		}, {
			"streams":	[{
					"socket":	5,
					"start":	162.0001380443573,
					"end":	164.00008606910706,
					"seconds":	1.9999480247497559,
					"bytes":	24903680,
					"bits_per_second":	99617308.817277208,
					"retransmits":	0,
					"snd_cwnd":	3350672,
					"rtt":	235484,
					"rttvar":	6174,
					"pmtu":	1500,
					"omitted":	false
				}],
			"sum":	{
				"start":	162.0001380443573,
				"end":	164.00008606910706,
				"seconds":	1.9999480247497559,
				"bytes":	24903680,
				"bits_per_second":	99617308.817277208,
				"retransmits":	0,
				"omitted":	false
			}
		}, {
			"streams":	[{
					"socket":	5,
					"start":	164.00008606910706,
					"end":	166.00008606910706,
					"seconds":	2,
					"bytes":	23592960,
					"bits_per_second":	94371840,
					"retransmits":	0,
					"snd_cwnd":	3350672,
					"rtt":	245496,
					"rttvar":	9944,
					"pmtu":	1500,
					"omitted":	false
				}],
			"sum":	{
				"start":	164.00008606910706,
				"end":	166.00008606910706,
				"seconds":	2,
				"bytes":	23592960,
				"bits_per_second":	94371840,
				"retransmits":	0,
				"omitted":	false
			}
		}, {
			"streams":	[{
					"socket":	5,
					"start":	166.00008606910706,
					"end":	167.71796917915344,
					"seconds":	1.7178831100463867,
					"bytes":	20971520,
					"bits_per_second":	97662151.178300932,
					"retransmits":	0,
					"snd_cwnd":	3350672,
					"rtt":	248808,
					"rttvar":	3633,
					"pmtu":	1500,
					"omitted":	false
				}],
			"sum":	{
				"start":	166.00008606910706,
				"end":	167.71796917915344,
				"seconds":	1.7178831100463867,
				"bytes":	20971520,
				"bits_per_second":	97662151.178300932,
				"retransmits":	0,
				"omitted":	false
			}
		}],
	"end":	{
		"streams":	[{
				"sender":	{
					"socket":	5,
					"start":	0,
					"end":	167.71796917915344,
					"seconds":	167.71796917915344,
					"bytes":	1073912488,
					"bits_per_second":	51224683.592626393,
					"retransmits":	13,
					"max_snd_cwnd":	4785640,
					"max_rtt":	488151,
					"min_rtt":	235484,
					"mean_rtt":	440205
				},
				"receiver":	{
					"socket":	5,
					"start":	0,
					"end":	168.10796093940735,
					"seconds":	167.71796917915344,
					"bytes":	1073912488,
					"bits_per_second":	51105848.027605541
				}
			}],
		"sum_sent":	{
			"start":	0,
			"end":	167.71796917915344,
			"seconds":	167.71796917915344,
			"bytes":	1073912488,
			"bits_per_second":	51224683.592626393,
			"retransmits":	13
		},
		"sum_received":	{
			"start":	0,
			"end":	168.10796093940735,
			"seconds":	168.10796093940735,
			"bytes":	1073912488,
			"bits_per_second":	51105848.027605541
		},
		"cpu_utilization_percent":	{
			"host_total":	0.56946140124016242,
			"host_user":	0.045106045807598652,
			"host_system":	0.52435594381578088,
			"remote_total":	0.2988923130697746,
			"remote_user":	0.026254344940771161,
			"remote_system":	0.27263829748783153
		},
		"sender_tcp_congestion":	"cubic",
		"receiver_tcp_congestion":	"cubic"
	}
}
